liftoff/__init__.py
liftoff/align_features.py
liftoff/aligned_seg.py
liftoff/extract_features.py
liftoff/feature_hierarchy.py
liftoff/find_best_mapping.py
liftoff/fix_overlapping_features.py
liftoff/lift_features.py
liftoff/liftoff_utils.py
liftoff/liftover_types.py
liftoff/merge_lifted_features.py
liftoff/new_feature.py
liftoff/polish.py
liftoff/run_liftoff.py
liftoff/write_new_gff.py
Liftoff-1.6.3.2.dist-info/LICENSE.md
Liftoff-1.6.3.2.dist-info/METADATA
Liftoff-1.6.3.2.dist-info/WHEEL
Liftoff-1.6.3.2.dist-info/entry_points.txt
Liftoff-1.6.3.2.dist-info/top_level.txt
Liftoff-1.6.3.2.dist-info/RECORD
