Metadata-Version: 2.1
Name: Liftoff
Version: 1.6.3.2
Summary: A gene annotation mapping tool
Home-page: https://github.com/ashumate/Liftoff
Author: Alaina Shumate
Author-email: ashumat2@jhmi.edu
License: UNKNOWN
Platform: UNKNOWN
Requires-Python: >=3.6
License-File: LICENSE.md
Requires-Dist: numpy (==1.21.0)
Requires-Dist: biopython (==1.76)
Requires-Dist: gffutils (==0.10.1)
Requires-Dist: networkx (==2.4)
Requires-Dist: pysam (==0.16.0.1)
Requires-Dist: pyfaidx (==0.5.8)
Requires-Dist: interlap (==0.2.6)
Requires-Dist: ujson (==3.2.0)
Requires-Dist: parasail (>=1.2.1)
